sheet_simulator/__init__.py
sheet_simulator/generator.py
sheet_simulator/simulator.py
sheet_simulator-0.1.1.dist-info/LICENSE
sheet_simulator-0.1.1.dist-info/METADATA
sheet_simulator-0.1.1.dist-info/WHEEL
sheet_simulator-0.1.1.dist-info/top_level.txt
sheet_simulator-0.1.1.dist-info/RECORD
